sonarqube/__init__.py
sonarqube/auth.py
sonarqube/client.py
sonarqube/exceptions.py
sonarqube/http.py
sonarqube/py.typed
sonarqube/api/__init__.py
sonarqube/api/applications.py
sonarqube/api/base.py
sonarqube/api/components.py
sonarqube/api/hotspots.py
sonarqube/api/issues.py
sonarqube/api/measures.py
sonarqube/api/projects.py
sonarqube/api/qualitygates.py
sonarqube/api/qualityprofiles.py
sonarqube/api/rules.py
sonarqube/api/settings.py
sonarqube/api/sources.py
sonarqube/api/system.py
sonarqube/api/user_tokens.py
sonarqube/api/users.py
sonarqube/models/__init__.py
sonarqube/models/applications.py
sonarqube/models/base.py
sonarqube/models/common.py
sonarqube/models/components.py
sonarqube/models/hotspots.py
sonarqube/models/issues.py
sonarqube/models/measures.py
sonarqube/models/projects.py
sonarqube/models/qualitygates.py
sonarqube/models/qualityprofiles.py
sonarqube/models/rules.py
sonarqube/models/settings.py
sonarqube/models/sources.py
sonarqube/models/system.py
sonarqube/models/user_tokens.py
sonarqube/models/users.py
sonarqube_sdk-0.1.0.dist-info/METADATA
sonarqube_sdk-0.1.0.dist-info/WHEEL
sonarqube_sdk-0.1.0.dist-info/licenses/LICENSE
sonarqube_sdk-0.1.0.dist-info/RECORD
