Metadata-Version: 2.4
Name: sonarqube-sdk
Version: 0.1.0
Summary: A fully-typed Python SDK for SonarQube API
Project-URL: Homepage, https://github.com/silasvasconcelos/sonarqube-sdk
Project-URL: Documentation, https://sonarqube-sdk.readthedocs.io
Project-URL: Repository, https://github.com/silasvasconcelos/sonarqube-sdk
Project-URL: Changelog, https://github.com/silasvasconcelos/sonarqube-sdk/blob/main/CHANGELOG.md
Project-URL: Issues, https://github.com/silasvasconcelos/sonarqube-sdk/issues
Author-email: Silas Vasconcelos <silasvasconcelos@hotmail.com.br>
Maintainer-email: Silas Vasconcelos <silasvasconcelos@hotmail.com.br>
License: MIT
License-File: LICENSE
Keywords: api,code-quality,sdk,sonarqube,static-analysis
Classifier: Development Status :: 4 - Beta
Classifier: Intended Audience :: Developers
Classifier: License :: OSI Approved :: MIT License
Classifier: Operating System :: OS Independent
Classifier: Programming Language :: Python :: 3
Classifier: Programming Language :: Python :: 3.9
Classifier: Programming Language :: Python :: 3.10
Classifier: Programming Language :: Python :: 3.11
Classifier: Programming Language :: Python :: 3.12
Classifier: Programming Language :: Python :: 3.13
Classifier: Topic :: Software Development :: Libraries :: Python Modules
Classifier: Topic :: Software Development :: Quality Assurance
Classifier: Typing :: Typed
Requires-Python: >=3.9
Requires-Dist: httpx>=0.24.0
Requires-Dist: pydantic>=2.0.0
Requires-Dist: typing-extensions>=4.0.0; python_version < '3.10'
Provides-Extra: dev
Requires-Dist: bandit>=1.7.0; extra == 'dev'
Requires-Dist: mypy>=1.0.0; extra == 'dev'
Requires-Dist: pytest-asyncio>=0.21.0; extra == 'dev'
Requires-Dist: pytest-cov>=4.0.0; extra == 'dev'
Requires-Dist: pytest>=7.0.0; extra == 'dev'
Requires-Dist: respx>=0.20.0; extra == 'dev'
Requires-Dist: ruff>=0.8.0; extra == 'dev'
Requires-Dist: tox-uv>=1.0.0; extra == 'dev'
Requires-Dist: tox>=4.0.0; extra == 'dev'
Provides-Extra: docs
Requires-Dist: sphinx-autodoc-typehints>=1.24.0; extra == 'docs'
Requires-Dist: sphinx-rtd-theme>=1.3.0; extra == 'docs'
Requires-Dist: sphinx>=6.0.0; extra == 'docs'
